{
  "interval": "100",
  "watcher": {
    "key": "",
    "type": "hexKey"
  },
  "managers": {
    "kovanbridgerouter": {
      "address": "0x0000000000000000000000000000000000000000",
      "domain": "3000",
      "name": "kovan",
      "rpcStyle": "ethereum",
      "connection": {
        "type": "http",
        "url": ""
      }
    },
    "alfajoresbridgerouter": {
      "address": "0x0000000000000000000000000000000000000000",
      "domain": "1000",
      "name": "alfajores",
      "rpcStyle": "ethereum",
      "connection": {
        "type": "http",
        "url": ""
      }
    }
  }
}
